Metadata-Version: 2.1
Name: eegpipline
Version: 0.1
Summary: Testing installation of Package
Home-page: UNKNOWN
Author: Marta Kubinska
Author-email: mk@optocuetics.com
License: MIT
Platform: UNKNOWN
License-File: License.txt
